tree_sitter_twolc-1.0.0.dist-info/RECORD
tree_sitter_twolc-1.0.0.dist-info/top_level.txt
tree_sitter_twolc-1.0.0.dist-info/METADATA
tree_sitter_twolc-1.0.0.dist-info/WHEEL
tree_sitter_twolc/__init__.pyi
tree_sitter_twolc/_binding.abi3.so
tree_sitter_twolc/py.typed
tree_sitter_twolc/binding.c
tree_sitter_twolc/__init__.py
tree_sitter_twolc/queries/highlights.scm
